searchpoi/__init__.py
searchpoi/searchpoi.py
searchpoi/tests/__init__.py
searchpoi/tests/test_searchpoi.py
searchpoi-0.0.1.dist-info/LICENSE
searchpoi-0.0.1.dist-info/METADATA
searchpoi-0.0.1.dist-info/WHEEL
searchpoi-0.0.1.dist-info/top_level.txt
searchpoi-0.0.1.dist-info/RECORD
