Metadata-Version: 2.1
Name: searchpoi
Version: 0.0.1
Summary: This package search Point of Interests inside a specific area using Overpass API.
Home-page: https://github.com/pypa/sampleproject
Author: Massimo Colombi
Author-email: massimo.colombi@librecamelot.org
License: UNKNOWN
Platform: UNKNOWN
Classifier: Programming Language :: Python :: 3
Classifier: License :: OSI Approved :: MIT License
Classifier: Operating System :: OS Independent
Requires-Python: >=3.6
